[
  {
    "id": "easefica_report",
    "label": "EaseFICA risk-rating report",
    "url": "https://admin.easefica.co.za",
    "accept": "application/pdf",
    "kind": "PDF report",
    "docs": ["easefica_risk_rating"]
  },
  {
    "id": "screening_shot",
    "label": "Dilisense PEP / sanctions screening",
    "url": "https://dilisense.com/en",
    "accept": "image/*",
    "kind": "screenshot",
    "docs": ["pep_screening"]
  },
  {
    "id": "tfs_screenshot",
    "label": "FIC Targeted Financial Sanctions (TFS) screening",
    "url": "https://tfs.fic.gov.za/Pages/Search",
    "accept": "image/*",
    "kind": "screenshot",
    "docs": ["fic_tfs_screenshot"]
  }
]
